MDC/__init__.py
mdcompiler-2021.4.1.dist-info/METADATA
mdcompiler-2021.4.1.dist-info/WHEEL
mdcompiler-2021.4.1.dist-info/entry_points.txt
mdcompiler-2021.4.1.dist-info/top_level.txt
mdcompiler-2021.4.1.dist-info/RECORD
