Metadata-Version: 2.1
Name: mdcompiler
Version: 2021.4.1
Summary: a free & OpenSource Markdown Compiler
Home-page: https://github.com/TechGeeks-Dev/MDC
Author: TechGeeks
Author-email: MDCompiler@tgeeks.cf
Maintainer: Rajdeep Malakar
Maintainer-email: Rajdeep@tgeeks.cf
License: UNKNOWN
Platform: UNKNOWN
Classifier: Programming Language :: Python :: 3
Classifier: License :: OSI Approved :: MIT License
Classifier: Operating System :: OS Independent
Requires-Python: >=3.6
Requires-Dist: markdown
